[
  {
    "id": "ac_1778419060231_2_1",
    "company_id": "c_1778419060231_2",
    "bank": "KBank",
    "status": "pending",
    "open_date": null,
    "blown_date": null,
    "monthly_fee": 8000,
    "payout": 13000,
    "contract_end": null,
    "notes": "",
    "monthly_net_price": {},
    "prorate_claimed_months": {},
    "created_at": "2026-05-10T13:17:50.951045+00:00",
    "compensation_price": 15000
  },
  {
    "id": "ac_1778419060231_2_2",
    "company_id": "c_1778419060231_2",
    "bank": "SCB",
    "status": "pending",
    "open_date": null,
    "blown_date": null,
    "monthly_fee": 8000,
    "payout": 13000,
    "contract_end": null,
    "notes": "",
    "monthly_net_price": {},
    "prorate_claimed_months": {},
    "created_at": "2026-05-10T13:17:51.050536+00:00",
    "compensation_price": 15000
  },
  {
    "id": "ac_1778419060231_2_3",
    "company_id": "c_1778419060231_2",
    "bank": "KTB",
    "status": "pending",
    "open_date": null,
    "blown_date": null,
    "monthly_fee": 8000,
    "payout": 13000,
    "contract_end": null,
    "notes": "",
    "monthly_net_price": {},
    "prorate_claimed_months": {},
    "created_at": "2026-05-10T13:17:51.159789+00:00",
    "compensation_price": 15000
  },
  {
    "id": "ac_1778419077610_1_1",
    "company_id": "c_1778419077610_1",
    "bank": "KBank",
    "status": "pending",
    "open_date": null,
    "blown_date": null,
    "monthly_fee": 8000,
    "payout": 13000,
    "contract_end": null,
    "notes": "",
    "monthly_net_price": {},
    "prorate_claimed_months": {},
    "created_at": "2026-05-10T13:18:07.73717+00:00",
    "compensation_price": 15000
  },
  {
    "id": "ac_1778419077610_1_2",
    "company_id": "c_1778419077610_1",
    "bank": "SCB",
    "status": "pending",
    "open_date": null,
    "blown_date": null,
    "monthly_fee": 8000,
    "payout": 13000,
    "contract_end": null,
    "notes": "",
    "monthly_net_price": {},
    "prorate_claimed_months": {},
    "created_at": "2026-05-10T13:18:07.837578+00:00",
    "compensation_price": 15000
  },
  {
    "id": "ac_1778419077610_1_3",
    "company_id": "c_1778419077610_1",
    "bank": "KTB",
    "status": "pending",
    "open_date": null,
    "blown_date": null,
    "monthly_fee": 8000,
    "payout": 13000,
    "contract_end": null,
    "notes": "",
    "monthly_net_price": {},
    "prorate_claimed_months": {},
    "created_at": "2026-05-10T13:18:07.977865+00:00",
    "compensation_price": 15000
  },
  {
    "id": "ac_1778419077610_2_1",
    "company_id": "c_1778419077610_2",
    "bank": "KBank",
    "status": "pending",
    "open_date": null,
    "blown_date": null,
    "monthly_fee": 8000,
    "payout": 13000,
    "contract_end": null,
    "notes": "",
    "monthly_net_price": {},
    "prorate_claimed_months": {},
    "created_at": "2026-05-10T13:18:08.34005+00:00",
    "compensation_price": 15000
  },
  {
    "id": "ac_1778419077610_2_2",
    "company_id": "c_1778419077610_2",
    "bank": "SCB",
    "status": "pending",
    "open_date": null,
    "blown_date": null,
    "monthly_fee": 8000,
    "payout": 13000,
    "contract_end": null,
    "notes": "",
    "monthly_net_price": {},
    "prorate_claimed_months": {},
    "created_at": "2026-05-10T13:18:08.484077+00:00",
    "compensation_price": 15000
  },
  {
    "id": "ac_1778419077610_2_3",
    "company_id": "c_1778419077610_2",
    "bank": "KTB",
    "status": "pending",
    "open_date": null,
    "blown_date": null,
    "monthly_fee": 8000,
    "payout": 13000,
    "contract_end": null,
    "notes": "",
    "monthly_net_price": {},
    "prorate_claimed_months": {},
    "created_at": "2026-05-10T13:18:08.586371+00:00",
    "compensation_price": 15000
  },
  {
    "id": "ac_1778419082087_1_1",
    "company_id": "c_1778419082087_1",
    "bank": "KBank",
    "status": "pending",
    "open_date": null,
    "blown_date": null,
    "monthly_fee": 8000,
    "payout": 13000,
    "contract_end": null,
    "notes": "",
    "monthly_net_price": {},
    "prorate_claimed_months": {},
    "created_at": "2026-05-10T13:18:12.251118+00:00",
    "compensation_price": 15000
  },
  {
    "id": "ac_1778419082087_1_2",
    "company_id": "c_1778419082087_1",
    "bank": "SCB",
    "status": "pending",
    "open_date": null,
    "blown_date": null,
    "monthly_fee": 8000,
    "payout": 13000,
    "contract_end": null,
    "notes": "",
    "monthly_net_price": {},
    "prorate_claimed_months": {},
    "created_at": "2026-05-10T13:18:12.349757+00:00",
    "compensation_price": 15000
  },
  {
    "id": "ac_1778419082087_1_3",
    "company_id": "c_1778419082087_1",
    "bank": "KTB",
    "status": "pending",
    "open_date": null,
    "blown_date": null,
    "monthly_fee": 8000,
    "payout": 13000,
    "contract_end": null,
    "notes": "",
    "monthly_net_price": {},
    "prorate_claimed_months": {},
    "created_at": "2026-05-10T13:18:12.445808+00:00",
    "compensation_price": 15000
  },
  {
    "id": "ac_1778419082087_2_1",
    "company_id": "c_1778419082087_2",
    "bank": "KBank",
    "status": "pending",
    "open_date": null,
    "blown_date": null,
    "monthly_fee": 8000,
    "payout": 13000,
    "contract_end": null,
    "notes": "",
    "monthly_net_price": {},
    "prorate_claimed_months": {},
    "created_at": "2026-05-10T13:18:12.795648+00:00",
    "compensation_price": 15000
  },
  {
    "id": "ac_1778419082087_2_2",
    "company_id": "c_1778419082087_2",
    "bank": "SCB",
    "status": "pending",
    "open_date": null,
    "blown_date": null,
    "monthly_fee": 8000,
    "payout": 13000,
    "contract_end": null,
    "notes": "",
    "monthly_net_price": {},
    "prorate_claimed_months": {},
    "created_at": "2026-05-10T13:18:12.923137+00:00",
    "compensation_price": 15000
  },
  {
    "id": "ac_1778419082087_2_3",
    "company_id": "c_1778419082087_2",
    "bank": "KTB",
    "status": "pending",
    "open_date": null,
    "blown_date": null,
    "monthly_fee": 8000,
    "payout": 13000,
    "contract_end": null,
    "notes": "",
    "monthly_net_price": {},
    "prorate_claimed_months": {},
    "created_at": "2026-05-10T13:18:13.031755+00:00",
    "compensation_price": 15000
  },
  {
    "id": "ac_1778425073379_1_1",
    "company_id": "c_1778425073379_1",
    "bank": "KBank",
    "status": "pending",
    "open_date": null,
    "blown_date": null,
    "monthly_fee": 8000,
    "payout": 13000,
    "contract_end": null,
    "notes": "",
    "monthly_net_price": {},
    "prorate_claimed_months": {},
    "created_at": "2026-05-10T14:58:03.568053+00:00",
    "compensation_price": 15000
  },
  {
    "id": "ac_1778425073379_1_2",
    "company_id": "c_1778425073379_1",
    "bank": "SCB",
    "status": "pending",
    "open_date": null,
    "blown_date": null,
    "monthly_fee": 8000,
    "payout": 13000,
    "contract_end": null,
    "notes": "",
    "monthly_net_price": {},
    "prorate_claimed_months": {},
    "created_at": "2026-05-10T14:58:03.673544+00:00",
    "compensation_price": 15000
  },
  {
    "id": "ac_1778425073379_1_3",
    "company_id": "c_1778425073379_1",
    "bank": "KTB",
    "status": "pending",
    "open_date": null,
    "blown_date": null,
    "monthly_fee": 8000,
    "payout": 13000,
    "contract_end": null,
    "notes": "",
    "monthly_net_price": {},
    "prorate_claimed_months": {},
    "created_at": "2026-05-10T14:58:03.777332+00:00",
    "compensation_price": 15000
  },
  {
    "id": "ac_1778425073379_2_1",
    "company_id": "c_1778425073379_2",
    "bank": "KBank",
    "status": "pending",
    "open_date": null,
    "blown_date": null,
    "monthly_fee": 8000,
    "payout": 13000,
    "contract_end": null,
    "notes": "",
    "monthly_net_price": {},
    "prorate_claimed_months": {},
    "created_at": "2026-05-10T14:58:04.106083+00:00",
    "compensation_price": 15000
  },
  {
    "id": "ac_1778425073379_2_2",
    "company_id": "c_1778425073379_2",
    "bank": "SCB",
    "status": "pending",
    "open_date": null,
    "blown_date": null,
    "monthly_fee": 8000,
    "payout": 13000,
    "contract_end": null,
    "notes": "",
    "monthly_net_price": {},
    "prorate_claimed_months": {},
    "created_at": "2026-05-10T14:58:04.21265+00:00",
    "compensation_price": 15000
  },
  {
    "id": "ac_1778425073379_2_3",
    "company_id": "c_1778425073379_2",
    "bank": "KTB",
    "status": "pending",
    "open_date": null,
    "blown_date": null,
    "monthly_fee": 8000,
    "payout": 13000,
    "contract_end": null,
    "notes": "",
    "monthly_net_price": {},
    "prorate_claimed_months": {},
    "created_at": "2026-05-10T14:58:04.661293+00:00",
    "compensation_price": 15000
  },
  {
    "id": "ac_1778418377681_1_1",
    "company_id": "c_1778418377681_1",
    "bank": "KBank",
    "status": "open",
    "open_date": "2026-02-02",
    "blown_date": null,
    "monthly_fee": 25000,
    "payout": 7500,
    "contract_end": null,
    "notes": "",
    "monthly_net_price": {},
    "prorate_claimed_months": {},
    "created_at": "2026-05-10T13:06:27.770664+00:00",
    "compensation_price": 15000
  },
  {
    "id": "ac_1778418377681_1_2",
    "company_id": "c_1778418377681_1",
    "bank": "SCB",
    "status": "pending",
    "open_date": null,
    "blown_date": null,
    "monthly_fee": 8000,
    "payout": 7500,
    "contract_end": null,
    "notes": "",
    "monthly_net_price": {},
    "prorate_claimed_months": {},
    "created_at": "2026-05-10T13:06:27.888041+00:00",
    "compensation_price": 15000
  },
  {
    "id": "ac_1778418377681_1_3",
    "company_id": "c_1778418377681_1",
    "bank": "KTB",
    "status": "pending",
    "open_date": null,
    "blown_date": null,
    "monthly_fee": 8000,
    "payout": 7500,
    "contract_end": null,
    "notes": "",
    "monthly_net_price": {},
    "prorate_claimed_months": {},
    "created_at": "2026-05-10T13:06:27.99262+00:00",
    "compensation_price": 15000
  },
  {
    "id": "ac_1778418256348_1_1",
    "company_id": "c_1778418256347_1",
    "bank": "KBank",
    "status": "open",
    "open_date": "2026-03-21",
    "blown_date": null,
    "monthly_fee": 25000,
    "payout": 7500,
    "contract_end": null,
    "notes": "",
    "monthly_net_price": {},
    "prorate_claimed_months": {},
    "created_at": "2026-05-10T13:04:26.500394+00:00",
    "compensation_price": 15000
  },
  {
    "id": "ac_1778418377681_2_1",
    "company_id": "c_1778418377681_2",
    "bank": "KBank",
    "status": "pending",
    "open_date": null,
    "blown_date": null,
    "monthly_fee": 8000,
    "payout": 7500,
    "contract_end": null,
    "notes": "",
    "monthly_net_price": {},
    "prorate_claimed_months": {},
    "created_at": "2026-05-10T13:06:28.317366+00:00",
    "compensation_price": 15000
  },
  {
    "id": "ac_1778418256348_1_2",
    "company_id": "c_1778418256347_1",
    "bank": "SCB",
    "status": "pending",
    "open_date": null,
    "blown_date": null,
    "monthly_fee": 8000,
    "payout": 7500,
    "contract_end": null,
    "notes": "",
    "monthly_net_price": {},
    "prorate_claimed_months": {},
    "created_at": "2026-05-10T13:04:26.59901+00:00",
    "compensation_price": 15000
  },
  {
    "id": "ac_1778418377681_2_2",
    "company_id": "c_1778418377681_2",
    "bank": "SCB",
    "status": "pending",
    "open_date": null,
    "blown_date": null,
    "monthly_fee": 8000,
    "payout": 7500,
    "contract_end": null,
    "notes": "",
    "monthly_net_price": {},
    "prorate_claimed_months": {},
    "created_at": "2026-05-10T13:06:28.415026+00:00",
    "compensation_price": 15000
  },
  {
    "id": "ac_1778418377681_2_3",
    "company_id": "c_1778418377681_2",
    "bank": "KTB",
    "status": "pending",
    "open_date": null,
    "blown_date": null,
    "monthly_fee": 8000,
    "payout": 7500,
    "contract_end": null,
    "notes": "",
    "monthly_net_price": {},
    "prorate_claimed_months": {},
    "created_at": "2026-05-10T13:06:28.52164+00:00",
    "compensation_price": 15000
  },
  {
    "id": "ac_1778418256348_1_3",
    "company_id": "c_1778418256347_1",
    "bank": "KTB",
    "status": "pending",
    "open_date": null,
    "blown_date": null,
    "monthly_fee": 8000,
    "payout": 7500,
    "contract_end": null,
    "notes": "",
    "monthly_net_price": {},
    "prorate_claimed_months": {},
    "created_at": "2026-05-10T13:04:26.697551+00:00",
    "compensation_price": 15000
  },
  {
    "id": "ac_1778418256348_2_1",
    "company_id": "c_1778418256348_2",
    "bank": "KBank",
    "status": "pending",
    "open_date": null,
    "blown_date": null,
    "monthly_fee": 8000,
    "payout": 7500,
    "contract_end": null,
    "notes": "",
    "monthly_net_price": {},
    "prorate_claimed_months": {},
    "created_at": "2026-05-10T13:04:27.01392+00:00",
    "compensation_price": 15000
  },
  {
    "id": "ac_1778418256348_2_2",
    "company_id": "c_1778418256348_2",
    "bank": "SCB",
    "status": "pending",
    "open_date": null,
    "blown_date": null,
    "monthly_fee": 8000,
    "payout": 7500,
    "contract_end": null,
    "notes": "",
    "monthly_net_price": {},
    "prorate_claimed_months": {},
    "created_at": "2026-05-10T13:04:27.110791+00:00",
    "compensation_price": 15000
  },
  {
    "id": "ac_1778418256348_2_3",
    "company_id": "c_1778418256348_2",
    "bank": "KTB",
    "status": "pending",
    "open_date": null,
    "blown_date": null,
    "monthly_fee": 8000,
    "payout": 7500,
    "contract_end": null,
    "notes": "",
    "monthly_net_price": {},
    "prorate_claimed_months": {},
    "created_at": "2026-05-10T13:04:27.209499+00:00",
    "compensation_price": 15000
  },
  {
    "id": "ac_1778418333806_1_1",
    "company_id": "c_1778418333806_1",
    "bank": "KBank",
    "status": "open",
    "open_date": "2026-02-02",
    "blown_date": null,
    "monthly_fee": 25000,
    "payout": 7500,
    "contract_end": null,
    "notes": "",
    "monthly_net_price": {},
    "prorate_claimed_months": {},
    "created_at": "2026-05-10T13:05:43.938489+00:00",
    "compensation_price": 15000
  },
  {
    "id": "ac_1778418333806_1_2",
    "company_id": "c_1778418333806_1",
    "bank": "SCB",
    "status": "pending",
    "open_date": null,
    "blown_date": null,
    "monthly_fee": 8000,
    "payout": 7500,
    "contract_end": null,
    "notes": "",
    "monthly_net_price": {},
    "prorate_claimed_months": {},
    "created_at": "2026-05-10T13:05:44.077358+00:00",
    "compensation_price": 15000
  },
  {
    "id": "ac_1778418333806_1_3",
    "company_id": "c_1778418333806_1",
    "bank": "KTB",
    "status": "pending",
    "open_date": null,
    "blown_date": null,
    "monthly_fee": 8000,
    "payout": 7500,
    "contract_end": null,
    "notes": "",
    "monthly_net_price": {},
    "prorate_claimed_months": {},
    "created_at": "2026-05-10T13:05:44.182017+00:00",
    "compensation_price": 15000
  },
  {
    "id": "ac_1778418333806_2_3",
    "company_id": "c_1778418333806_2",
    "bank": "KTB",
    "status": "pending",
    "open_date": null,
    "blown_date": null,
    "monthly_fee": 8000,
    "payout": 7500,
    "contract_end": null,
    "notes": "",
    "monthly_net_price": {},
    "prorate_claimed_months": {},
    "created_at": "2026-05-10T13:05:44.713976+00:00",
    "compensation_price": 15000
  },
  {
    "id": "ac_1778418333806_2_1",
    "company_id": "c_1778418333806_2",
    "bank": "KBank",
    "status": "pending",
    "open_date": null,
    "blown_date": null,
    "monthly_fee": 8000,
    "payout": 7500,
    "contract_end": null,
    "notes": "",
    "monthly_net_price": {},
    "prorate_claimed_months": {},
    "created_at": "2026-05-10T13:05:44.503877+00:00",
    "compensation_price": 15000
  },
  {
    "id": "ac_1778418333806_2_2",
    "company_id": "c_1778418333806_2",
    "bank": "SCB",
    "status": "pending",
    "open_date": null,
    "blown_date": null,
    "monthly_fee": 8000,
    "payout": 7500,
    "contract_end": null,
    "notes": "",
    "monthly_net_price": {},
    "prorate_claimed_months": {},
    "created_at": "2026-05-10T13:05:44.60539+00:00",
    "compensation_price": 15000
  },
  {
    "id": "ac_1778419052530_1_1",
    "company_id": "c_1778419052530_1",
    "bank": "KBank",
    "status": "pending",
    "open_date": null,
    "blown_date": null,
    "monthly_fee": 8000,
    "payout": 13000,
    "contract_end": null,
    "notes": "",
    "monthly_net_price": {},
    "prorate_claimed_months": {},
    "created_at": "2026-05-10T13:17:42.655444+00:00",
    "compensation_price": 15000
  },
  {
    "id": "ac_1778419052530_1_2",
    "company_id": "c_1778419052530_1",
    "bank": "SCB",
    "status": "pending",
    "open_date": null,
    "blown_date": null,
    "monthly_fee": 8000,
    "payout": 13000,
    "contract_end": null,
    "notes": "",
    "monthly_net_price": {},
    "prorate_claimed_months": {},
    "created_at": "2026-05-10T13:17:42.763873+00:00",
    "compensation_price": 15000
  },
  {
    "id": "ac_1778419052530_1_3",
    "company_id": "c_1778419052530_1",
    "bank": "KTB",
    "status": "pending",
    "open_date": null,
    "blown_date": null,
    "monthly_fee": 8000,
    "payout": 13000,
    "contract_end": null,
    "notes": "",
    "monthly_net_price": {},
    "prorate_claimed_months": {},
    "created_at": "2026-05-10T13:17:42.875447+00:00",
    "compensation_price": 15000
  },
  {
    "id": "ac_1778419052530_2_1",
    "company_id": "c_1778419052530_2",
    "bank": "KBank",
    "status": "pending",
    "open_date": null,
    "blown_date": null,
    "monthly_fee": 8000,
    "payout": 13000,
    "contract_end": null,
    "notes": "",
    "monthly_net_price": {},
    "prorate_claimed_months": {},
    "created_at": "2026-05-10T13:17:43.228728+00:00",
    "compensation_price": 15000
  },
  {
    "id": "ac_1778419052530_2_2",
    "company_id": "c_1778419052530_2",
    "bank": "SCB",
    "status": "pending",
    "open_date": null,
    "blown_date": null,
    "monthly_fee": 8000,
    "payout": 13000,
    "contract_end": null,
    "notes": "",
    "monthly_net_price": {},
    "prorate_claimed_months": {},
    "created_at": "2026-05-10T13:17:43.342774+00:00",
    "compensation_price": 15000
  },
  {
    "id": "ac_1778419052530_2_3",
    "company_id": "c_1778419052530_2",
    "bank": "KTB",
    "status": "pending",
    "open_date": null,
    "blown_date": null,
    "monthly_fee": 8000,
    "payout": 13000,
    "contract_end": null,
    "notes": "",
    "monthly_net_price": {},
    "prorate_claimed_months": {},
    "created_at": "2026-05-10T13:17:43.455206+00:00",
    "compensation_price": 15000
  },
  {
    "id": "ac_1778419060231_1_1",
    "company_id": "c_1778419060231_1",
    "bank": "KBank",
    "status": "pending",
    "open_date": null,
    "blown_date": null,
    "monthly_fee": 8000,
    "payout": 13000,
    "contract_end": null,
    "notes": "",
    "monthly_net_price": {},
    "prorate_claimed_months": {},
    "created_at": "2026-05-10T13:17:50.376413+00:00",
    "compensation_price": 15000
  },
  {
    "id": "ac_1778419060231_1_2",
    "company_id": "c_1778419060231_1",
    "bank": "SCB",
    "status": "pending",
    "open_date": null,
    "blown_date": null,
    "monthly_fee": 8000,
    "payout": 13000,
    "contract_end": null,
    "notes": "",
    "monthly_net_price": {},
    "prorate_claimed_months": {},
    "created_at": "2026-05-10T13:17:50.476947+00:00",
    "compensation_price": 15000
  },
  {
    "id": "ac_1778419060231_1_3",
    "company_id": "c_1778419060231_1",
    "bank": "KTB",
    "status": "pending",
    "open_date": null,
    "blown_date": null,
    "monthly_fee": 8000,
    "payout": 13000,
    "contract_end": null,
    "notes": "",
    "monthly_net_price": {},
    "prorate_claimed_months": {},
    "created_at": "2026-05-10T13:17:50.596886+00:00",
    "compensation_price": 15000
  }
]